gql_schema_codegen/__init__.py
gql_schema_codegen/__main__.py
gql_schema_codegen/base/__init__.py
gql_schema_codegen/base/base.py
gql_schema_codegen/block/__init__.py
gql_schema_codegen/block/block.py
gql_schema_codegen/constants/__init__.py
gql_schema_codegen/constants/constants.py
gql_schema_codegen/dependency/__init__.py
gql_schema_codegen/dependency/dependency.py
gql_schema_codegen/scalar/__init__.py
gql_schema_codegen/scalar/scalar.py
gql_schema_codegen/schema/__init__.py
gql_schema_codegen/schema/schema.py
gql_schema_codegen/union/__init__.py
gql_schema_codegen/union/union.py
gql_schema_codegen/utils/__init__.py
gql_schema_codegen/utils/pascal_case.py
tests/__init__.py
tests/test_simple_schema.py
gql_schema_codegen-1.0.1.dist-info/LICENSE
gql_schema_codegen-1.0.1.dist-info/METADATA
gql_schema_codegen-1.0.1.dist-info/WHEEL
gql_schema_codegen-1.0.1.dist-info/top_level.txt
gql_schema_codegen-1.0.1.dist-info/RECORD
