Metadata-Version: 2.1
Name: gql-schema-codegen
Version: 1.0.1
Summary: A module to generate Python typings from a GrapqhQL schema
Home-page: https://github.com/sauldom102/gql_schema_codegen
Author: Saul Dominguez
Author-email: saulydominguez@gmail.com
License: UNKNOWN
Platform: UNKNOWN
Classifier: Programming Language :: Python :: 3
Classifier: License :: OSI Approved :: MIT License
Classifier: Operating System :: OS Independent
License-File: LICENSE
Requires-Dist: graphql-core (==3.2.0)
Requires-Dist: graphqlclient (==0.2.4)
Requires-Dist: argparse (==1.4.0)
Requires-Dist: pytest-snapshot (==0.8.1)
Requires-Dist: pytest (==7.1.1)
Requires-Dist: PyYAML (==6.0)
